[
null,
{"id":1,"expanded":false,"name":"MAP001","order":1,"parentId":0,"scrollX":818,"scrollY":448},
{"id":2,"expanded":false,"name":"02Nymph","order":4,"parentId":4,"scrollX":534,"scrollY":305},
{"id":3,"expanded":false,"name":"04Aphrodite","order":6,"parentId":4,"scrollX":534,"scrollY":319},
{"id":4,"expanded":true,"name":"Greek","order":2,"parentId":0,"scrollX":534,"scrollY":305},
{"id":5,"expanded":true,"name":"Egyptian","order":26,"parentId":0,"scrollX":534,"scrollY":319},
{"id":6,"expanded":false,"name":"01Heimdall","order":63,"parentId":50,"scrollX":818,"scrollY":448},
{"id":7,"expanded":false,"name":"02Kraken","order":45,"parentId":50,"scrollX":832,"scrollY":640},
{"id":8,"expanded":false,"name":"03Skoll","order":46,"parentId":50,"scrollX":819,"scrollY":453},
{"id":9,"expanded":true,"name":"Japanese","order":64,"parentId":0,"scrollX":534,"scrollY":319},
{"id":10,"expanded":false,"name":"11Tsukuyomi","order":78,"parentId":9,"scrollX":818,"scrollY":448},
{"id":11,"expanded":false,"name":"12Izanagi","order":79,"parentId":9,"scrollX":818,"scrollY":448},
{"id":12,"expanded":false,"name":"12Izanami","order":80,"parentId":9,"scrollX":818,"scrollY":448},
{"id":13,"expanded":false,"name":"12Duelist","order":81,"parentId":9,"scrollX":818,"scrollY":448},
{"id":14,"expanded":false,"name":"11Artemis","order":16,"parentId":4,"scrollX":650.4,"scrollY":366},
{"id":15,"expanded":false,"name":"01Athena","order":3,"parentId":4,"scrollX":534,"scrollY":319},
{"id":16,"expanded":false,"name":"03Medusa","order":5,"parentId":4,"scrollX":832,"scrollY":640},
{"id":17,"expanded":false,"name":"05Athena2","order":7,"parentId":4,"scrollX":832,"scrollY":640},
{"id":18,"expanded":false,"name":"06Minotaur","order":8,"parentId":4,"scrollX":650.4,"scrollY":366},
{"id":19,"expanded":false,"name":"07Hephaestus","order":9,"parentId":4,"scrollX":832,"scrollY":640},
{"id":20,"expanded":false,"name":"06Harpy","order":11,"parentId":4,"scrollX":818,"scrollY":448},
{"id":21,"expanded":false,"name":"07Demeter","order":12,"parentId":4,"scrollX":818,"scrollY":448},
{"id":22,"expanded":false,"name":"08Dionysus","order":13,"parentId":4,"scrollX":728,"scrollY":409.77777777777777},
{"id":23,"expanded":false,"name":"08Ares","order":10,"parentId":4,"scrollX":832,"scrollY":640},
{"id":24,"expanded":false,"name":"09Hermes","order":14,"parentId":4,"scrollX":832,"scrollY":640},
{"id":25,"expanded":false,"name":"10Apollo","order":15,"parentId":4,"scrollX":818,"scrollY":448},
{"id":26,"expanded":false,"name":"11Chimera","order":17,"parentId":4,"scrollX":832,"scrollY":640},
{"id":27,"expanded":false,"name":"12Cyclops","order":18,"parentId":4,"scrollX":832,"scrollY":640},
{"id":28,"expanded":false,"name":"12Hera","order":19,"parentId":4,"scrollX":832,"scrollY":640},
{"id":29,"expanded":false,"name":"13Zeus","order":20,"parentId":4,"scrollX":818,"scrollY":448},
{"id":30,"expanded":false,"name":"13Poseidon","order":21,"parentId":4,"scrollX":534,"scrollY":319},
{"id":31,"expanded":false,"name":"14Final","order":22,"parentId":4,"scrollX":832,"scrollY":640},
{"id":32,"expanded":false,"name":"15Final02","order":23,"parentId":4,"scrollX":534,"scrollY":319},
{"id":33,"expanded":false,"name":"01Leviathan","order":27,"parentId":5,"scrollX":832,"scrollY":640},
{"id":34,"expanded":false,"name":"02Beset","order":28,"parentId":5,"scrollX":818,"scrollY":448},
{"id":35,"expanded":false,"name":"03Duelist","order":29,"parentId":5,"scrollX":832,"scrollY":640},
{"id":36,"expanded":false,"name":"04Mummy","order":30,"parentId":5,"scrollX":532,"scrollY":319},
{"id":37,"expanded":false,"name":"05Sphinx","order":31,"parentId":5,"scrollX":817,"scrollY":455.5},
{"id":38,"expanded":false,"name":"06Sekhmet","order":32,"parentId":5,"scrollX":832,"scrollY":640},
{"id":39,"expanded":false,"name":"06Phoenix","order":33,"parentId":5,"scrollX":832,"scrollY":640},
{"id":40,"expanded":false,"name":"06Bast","order":34,"parentId":5,"scrollX":981.5999999999999,"scrollY":537.6},
{"id":41,"expanded":false,"name":"07Serket","order":35,"parentId":5,"scrollX":832,"scrollY":640},
{"id":42,"expanded":false,"name":"08Osiris","order":36,"parentId":5,"scrollX":819,"scrollY":453},
{"id":43,"expanded":false,"name":"08Horus","order":37,"parentId":5,"scrollX":981.5999999999999,"scrollY":537.6},
{"id":44,"expanded":false,"name":"09Apophis","order":38,"parentId":5,"scrollX":832,"scrollY":640},
{"id":45,"expanded":false,"name":"10Anubis","order":39,"parentId":5,"scrollX":832,"scrollY":640},
{"id":46,"expanded":false,"name":"11Isis","order":40,"parentId":5,"scrollX":832,"scrollY":640},
{"id":47,"expanded":false,"name":"11Ra","order":41,"parentId":5,"scrollX":832,"scrollY":640},
{"id":48,"expanded":false,"name":"11Set","order":42,"parentId":5,"scrollX":819,"scrollY":453},
{"id":49,"expanded":false,"name":"12FinalEgypt","order":43,"parentId":5,"scrollX":818,"scrollY":448},
{"id":50,"expanded":true,"name":"Norse","order":44,"parentId":0,"scrollX":534,"scrollY":319},
{"id":51,"expanded":false,"name":"04Fenrir","order":47,"parentId":50,"scrollX":832,"scrollY":640},
{"id":52,"expanded":false,"name":"05Skadi","order":48,"parentId":50,"scrollX":832,"scrollY":640},
{"id":53,"expanded":false,"name":"04Valkyrie","order":49,"parentId":50,"scrollX":819,"scrollY":453},
{"id":54,"expanded":false,"name":"05Sigurd","order":50,"parentId":50,"scrollX":819,"scrollY":453},
{"id":55,"expanded":false,"name":"06Loki","order":51,"parentId":50,"scrollX":819,"scrollY":453},
{"id":56,"expanded":false,"name":"07Idun","order":52,"parentId":50,"scrollX":819,"scrollY":453},
{"id":57,"expanded":false,"name":"08Norns","order":53,"parentId":50,"scrollX":818,"scrollY":448},
{"id":58,"expanded":false,"name":"09Balder","order":54,"parentId":50,"scrollX":832,"scrollY":640},
{"id":59,"expanded":false,"name":"09Nidhogg","order":55,"parentId":50,"scrollX":819,"scrollY":453},
{"id":60,"expanded":false,"name":"10Freyja","order":56,"parentId":50,"scrollX":819,"scrollY":453},
{"id":61,"expanded":false,"name":"10Yggdrasil","order":57,"parentId":50,"scrollX":832,"scrollY":640},
{"id":62,"expanded":false,"name":"11Loki","order":59,"parentId":50,"scrollX":818,"scrollY":448},
{"id":63,"expanded":false,"name":"12Thor","order":60,"parentId":50,"scrollX":832,"scrollY":640},
{"id":64,"expanded":false,"name":"12Odin","order":61,"parentId":50,"scrollX":818,"scrollY":448},
{"id":65,"expanded":false,"name":"12Hel","order":62,"parentId":50,"scrollX":819,"scrollY":453},
{"id":66,"expanded":false,"name":"01Kasa-Obake","order":65,"parentId":9,"scrollX":534,"scrollY":319},
{"id":67,"expanded":false,"name":"02Hanako","order":66,"parentId":9,"scrollX":534,"scrollY":305},
{"id":68,"expanded":true,"name":"10Tyr","order":58,"parentId":50,"scrollX":819,"scrollY":453},
{"id":69,"expanded":false,"name":"03Uzume","order":67,"parentId":9,"scrollX":534,"scrollY":305},
{"id":70,"expanded":false,"name":"04Yuki-Onna","order":68,"parentId":9,"scrollX":534,"scrollY":319},
{"id":71,"expanded":false,"name":"04Kirin","order":69,"parentId":9,"scrollX":534,"scrollY":319},
{"id":72,"expanded":false,"name":"05Fujin","order":70,"parentId":9,"scrollX":534,"scrollY":319},
{"id":73,"expanded":false,"name":"06Raijin","order":71,"parentId":9,"scrollX":832,"scrollY":640},
{"id":74,"expanded":false,"name":"07InariOkami","order":72,"parentId":9,"scrollX":981.5999999999999,"scrollY":537.6},
{"id":75,"expanded":false,"name":"08Toyotama","order":73,"parentId":9,"scrollX":534,"scrollY":319},
{"id":76,"expanded":false,"name":"08Susano","order":74,"parentId":9,"scrollX":832,"scrollY":640},
{"id":77,"expanded":false,"name":"09Ryujin","order":75,"parentId":9,"scrollX":534,"scrollY":305},
{"id":78,"expanded":false,"name":"10Prelude","order":76,"parentId":9,"scrollX":534,"scrollY":319},
{"id":79,"expanded":false,"name":"11Amaterasu","order":77,"parentId":9,"scrollX":832,"scrollY":640},
{"id":80,"expanded":false,"name":"13Final01","order":82,"parentId":9,"scrollX":818,"scrollY":448},
{"id":81,"expanded":false,"name":"13Final02","order":83,"parentId":9,"scrollX":818,"scrollY":448},
{"id":82,"expanded":false,"name":"13Hades","order":84,"parentId":9,"scrollX":534,"scrollY":305},
{"id":83,"expanded":false,"name":"14Final02","order":85,"parentId":9,"scrollX":532,"scrollY":319},
{"id":84,"expanded":false,"name":"14Final01","order":86,"parentId":9,"scrollX":532,"scrollY":319},
{"id":85,"expanded":true,"name":"TutorialScene","order":24,"parentId":4,"scrollX":534,"scrollY":305},
{"id":86,"expanded":false,"name":"Prelogue","order":25,"parentId":4,"scrollX":817,"scrollY":455.5}
]